lock_with_timeout/__init__.py
lock_with_timeout-0.1.1.dist-info/DESCRIPTION.rst
lock_with_timeout-0.1.1.dist-info/METADATA
lock_with_timeout-0.1.1.dist-info/RECORD
lock_with_timeout-0.1.1.dist-info/WHEEL
lock_with_timeout-0.1.1.dist-info/metadata.json
lock_with_timeout-0.1.1.dist-info/top_level.txt
tests/__init__.py
tests/test_sample.py
