Metadata-Version: 2.0
Name: lock-with-timeout
Version: 0.1.1
Summary: Theading lock with timeout
Home-page: https://github.com/fx-kirin/lock_with_timeout
Author: fx-kirin
Author-email: fx.kirin@gmail.com
License: UNKNOWN
Platform: UNKNOWN
Classifier: Development Status :: 2 - Pre-Alpha
Classifier: Programming Language :: Python
Classifier: Programming Language :: Python :: 2
Classifier: Programming Language :: Python :: 2.7
Classifier: Programming Language :: Python :: 3
Classifier: Programming Language :: Python :: 3.4
Classifier: Programming Language :: Python :: 3.5
